link_sync/__main__.py
link_sync/apis.py
link_sync/printers.py
link_sync/storage.py
link_sync/utilities.py
link_sync-0.2.5.dist-info/AUTHORS.txt
link_sync-0.2.5.dist-info/LICENSE.txt
link_sync-0.2.5.dist-info/METADATA
link_sync-0.2.5.dist-info/WHEEL
link_sync-0.2.5.dist-info/entry_points.txt
link_sync-0.2.5.dist-info/top_level.txt
link_sync-0.2.5.dist-info/RECORD
