Metadata-Version: 2.1
Name: link-sync
Version: 0.2.5
Summary: Synchronize GCode files across your printer farm.
Home-page: https://github.com/mkoistinen/link-sync
Author: Martin Koistinen
Author-email: mkoistinen@gmail.com
License: Apache-2.0
Keywords: prusalink,prusa-link
Classifier: Development Status :: 3 - Alpha
Classifier: License :: OSI Approved :: Apache Software License
Classifier: Programming Language :: Python :: 3
Classifier: Programming Language :: Python :: 3.8
Classifier: Programming Language :: Python :: 3.9
Classifier: Programming Language :: Python :: 3.10
Classifier: Programming Language :: Python :: 3.11
Classifier: Environment :: Console
Requires-Python: >=3.10
License-File: LICENSE.txt
License-File: AUTHORS.txt
Requires-Dist: requests
Requires-Dist: rich
Requires-Dist: pyyaml
